sbd.py
dataset/industrial.py
etsc/etsc.py
ieral/ieral.py
ieral/noise_estimation.py
segmentation/segmentation.py
ieral-0.0.2.dist-info/METADATA
ieral-0.0.2.dist-info/WHEEL
ieral-0.0.2.dist-info/top_level.txt
ieral-0.0.2.dist-info/RECORD
