Metadata-Version: 2.1
Name: ieral
Version: 0.0.2
Summary: Implementation of Iterative ERAL algorithm (Stržinar et al., 2024)
Author-email: Žiga Stržinar <ziga.strzinar@ijs.si>
Project-URL: Homepage, https://repo.ijs.si/zstrzinar/ieral
Classifier: Programming Language :: Python :: 3
Classifier: Operating System :: OS Independent
Requires-Python: >=3.11
Requires-Dist: dtw-python>=1.3.0
Requires-Dist: matplotlib>=3.6.2
Requires-Dist: numpy<2.0.0,>=1.23.4
Requires-Dist: pandas<2.0.0,>=1.4.3
Requires-Dist: python-dateutil>=2.8.2
Requires-Dist: scikit-learn>=1.2.1
Requires-Dist: scipy>=1.9.0
Requires-Dist: tslearn>=0.6.3
Requires-Dist: line-profiler>=4.1.2
Requires-Dist: numba<0.60.0,>=0.58.1
Requires-Dist: eral>=1.0.0
